setup.py
sunnyday_yb/__init__.py
sunnyday_yb/sunnyday.py
sunnyday_yb.egg-info/PKG-INFO
sunnyday_yb.egg-info/SOURCES.txt
sunnyday_yb.egg-info/dependency_links.txt
sunnyday_yb.egg-info/requires.txt
sunnyday_yb.egg-info/top_level.txt