Metadata-Version: 2.1
Name: sunnyday-yb
Version: 2.0.0
Summary: Weather forecast for the next 12 hours
Author: Yunbi Nam
Author-email: yunbipython@gmail.com
License: MIT
